microsoft_security_utilities_secret_masker/__init__.py
microsoft_security_utilities_secret_masker/detection.py
microsoft_security_utilities_secret_masker/regex_pattern.py
microsoft_security_utilities_secret_masker/rw_lock.py
microsoft_security_utilities_secret_masker/secret_masker.py
microsoft_security_utilities_secret_masker/util.py
microsoft_security_utilities_secret_masker/GeneratedRegexPatterns/HighConfidenceSecurityModels.json
microsoft_security_utilities_secret_masker/GeneratedRegexPatterns/LowConfidenceSecurityModels.json
microsoft_security_utilities_secret_masker/GeneratedRegexPatterns/MediumConfidenceSecurityModels.json
microsoft_security_utilities_secret_masker/GeneratedRegexPatterns/PreciselyClassifiedSecurityKeys.json
microsoft_security_utilities_secret_masker/GeneratedRegexPatterns/UnclassifiedPotentialSecurityKeys.json
microsoft_security_utilities_secret_masker/GeneratedRegexPatterns/__init__.py
microsoft_security_utilities_secret_masker-1.0.0b2.dist-info/LICENSE
microsoft_security_utilities_secret_masker-1.0.0b2.dist-info/METADATA
microsoft_security_utilities_secret_masker-1.0.0b2.dist-info/WHEEL
microsoft_security_utilities_secret_masker-1.0.0b2.dist-info/top_level.txt
microsoft_security_utilities_secret_masker-1.0.0b2.dist-info/RECORD
