Metadata-Version: 2.1
Name: microsoft-security-utilities-secret-masker
Version: 1.0.0b2
Summary: A tool for detecting and masking secrets
Author: Microsoft Corporation
Author-email: azpycli@microsoft.com
License: MIT
License-File: LICENSE
